Workbook

Sheet PROCESSOS
A1: PROCESSOS - CONTROLE DE PROCESSOS TRABALHISTAS
A2: N° PROCESSO | B2: DATA DE AJUIZ. | C2: TRT / REGIÃO | D2: VARA DO TRABALHO | E2: RECLAMANTE | F2: RECLAMADA | G2: ADVOGADO RECLAMADO | H2: ADVOGADO RECLAMANTE | I2: VALOR DA CAUSA | J2: MATÉRIA / PEDIDOS FORMULADOS | K2: FASE PROCESSUAL | L2: DATA DA SENTENÇA | M2: SITUAÇÃO | N2: DATA DA PROX. AUDIÊNCIA | O2: VALOR CONDENAÇÃO | P2: STATUS | Q2: ACORDO | R2: VALOR DO ACORDO | S2: CUSTO TOTAL | T2: ECONOMIA | U2: OBSERVAÇÕES
A3: 0000615-59.2025.5.14.0111 | B3: 45978 | C3: TRT 14° | D3: PIMENTA BUENO | E3: CELIO CRESSENCIO DE PAULA | F3: VF GOMES CONSTRUTORA | G3: CLEITON DA SILVA ISABEL | H3: GLORIA CHRIS GORDON | I3: 184210.01 | J3: ADICIONAL DE HORAS EXTRAS, ADICIONAL NOTURNO, INDENIZAÇÃO POR DANO MORAL, INTEGRAÇÃO EM VERBAS RESCISÓRIAS, INTERVALO INTERJORNADAS, INTERVALO INTRAJORNADA, MULTA DO ARTIGO 467 DA CLT | K3: RECURSO | L3: 46078 | M3: AGUARDANDO PERICIA | N3: - | O3: 236514.06 | P3: EM ANDAMENTO | Q3: - | R3: - | S3: 236514.06 | T3: =I3-S3 -> -52304.05 | U3: -
A4: 0000616-44.2025.5.14.0111 | B4: 45978 | C4: TRT 14° | D4: JARU | E4: CELIO CRESSENCIO DE PAULA | F4: VF GOMES CONSTRUTORA | G4: ANA KAROLINE DA SILVA | H4: GLORIA CHRIS GORDON | I4: 14536.37 | J4: ADICIONAL DE INSALUBRIDADE, ANOTAÇÃO/BAIXA/RETIFICAÇÃO, HONORÁRIOS ADVOCATÍCIOS, MULTA DO ARTIGO 467 DA CLT | K4: INSTRUÇÃO | L4: - | M4: AGUARDANDO AUDIÊNCIA | N4: 06/07/2026, ÀS 11:00. | O4: AGUARDANDO AUDIÊNCIA | P4: EM ANDAMENTO | Q4: - | R4: - | S4: - | T4: - | U4: -
A5: 0000667-71.2025.5.14.0041 | B5: 45945 | C5: TRT 14° | D5: VILHENA | E5: REINILTON SERGIO DE SOUZA | F5: VF GOMES CONSTRUTORA | G5: ANA KAROLINE DA SILVA | H5: GLORIA CHRIS GORDON | I5: 5525.52 | J5: ADICIONAL DE INSALUBRIDADE, ANOTAÇÃO/BAIXA/RETIFICAÇÃO, MULTA DO ARTIGO 467 DA CLT | K5: INSTRUÇÃO | L5: - | M5: AGUARDANDO PERICIA | N5: - | O5: AGUARDANDO PERICIA | P5: EM ANDAMENTO | Q5: - | R5: - | S5: - | T5: - | U5: -
A6: 0000674-63.2025.5.14.0041 | B6: 45947 | C6: TRT 14° | D6: PIMENTA BUENO | E6: REINILTON SERGIO DE SOUZA | F6: VF GOMES CONSTRUTORA | G6: CLEITON DA SILVA ISABEL | H6: GLORIA CHRIS GORDON | I6: 148402.05 | J6: INTEGRAÇÃO EM VERBAS RESCISÓRIAS, ADICIONAL NOTURNO, ADICIONAL DE HORAS EXTRAS, HONORÁRIOS ADVOCATÍCIOS, INDENIZAÇÃO POR DANO MORAL, INTERVALO INTRAJORNADA, MULTA DO ARTIGO 467 DA CLT, SALÁRIO POR ACÚMULO DE CARGO/FUNÇÃO, SALÁRIO POR FORA - INTEGRAÇÃO | K6: RECURSO | L6: 46052 | M6: AGUARDANDO PERICIA | N6: - | O6: 317.17 | P6: EM ANDAMENTO | Q6: - | R6: - | S6: 317.17 | T6: =I6-S6 -> 148084.88 | U6: -
A7: 0000826-22.2025.5.14.0006 | B7: 45994 | C7: TRT 14° | D7: JARU | E7: REGINALDO PEREIRA DOS SANTOS | F7: VF GOMES CONSTRUTORA | G7: CLEITON DA SILVA ISABEL | H7: GUILHERME RIBEIRO VENTURIN / JACKSON FRANCISCO OLIVEIRA | I7: 57652.63 | J7: ADICIONAL DE INSALUBRIDADE, ACÚMULO DE FUNÇÃO, ADICIONAL DE PERICULOSIDADE, EQUIPAMENTO DE PROTEÇÃO INDIVIDUAL - EPI, SALÁRIO POR ACÚMULO DE CARGO/FUNÇÃO | K7: RECURSO | L7: 46149 | M7: AGUARDANDO PERICIA | N7: - | O7: ZERADO | P7: EM ANDAMENTO | Q7: - | R7: - | S7: ZERADO | T7: =I7 -> 57652.63 | U7: -
A8: 0001046-03.2025.5.14.0141 | B8: 46015 | C8: TRT 14° | D8: VILHENA | E8: WEVERTON FELIPE RIBEIRO DE OLIVEIRA | F8: VF GOMES CONSTRUTORA | G8: ANA KAROLINE DA SILVA | H8: CRISDAINE MICAELI SILVA FAVALESSA SOUZA | I8: 186643.84 | J8: SUCUMBENCIAIS, ADICIONAL NOTURNO, ADICIONAL DE HORAS EXTRAS, FGTS, FGTS, HORAS EXTRAS, HORAS EXTRAS, INTERVALO INTERJORNADAS, INTERVALO INTRAJORNADA, MULTA DE 40% DO FGTS, PRORROGAÇÃO DO HORÁRIO NOTURNO, REFLEXOS, REPOUSO SEMANAL REMUNERADO E FERIADO | K8: EXECUÇÃO | L8: 46078 | M8: AGUARDANDO CUMPRIMENTO DO ACORDO | N8: - | O8: 254939.65 | P8: EM ANDAMENTO | Q8: - | R8: - | S8: 172380 | T8: =I8-S8 -> 14263.84 | U8: -
A9: 0000054-98.2026.5.14.0111 | B9: 46059 | C9: TRT 14° | D9: PIMENTA BUENO | E9: JESSE RODRIGUES OLIVEIRA | F9: VF GOMES CONSTRUTORA | G9: CLEITON DA SILVA ISABEL / ANA KAROLINE DA SILVA | H9: CRISDAINE MICAELI SILVA FAVALESSA SOUZA | I9: 152125.64 | J9: ADICIONAL DE HORAS EXTRAS, ADICIONAL NOTURNO, ADICIONAL DE PERICULOSIDADE, FGTS, FGTS, HONORÁRIOS ADVOCATÍCIOS, HORAS EXTRAS, HORAS EXTRAS, INDENIZAÇÃO POR DANO MATERIAL, INDENIZAÇÃO POR DANO MORAL, INTERVALO INTERJORNADAS, INTERVALO INTRAJORNADA, INTERVALO INTRAJORNADA, MULTA DE 40% DO FGTS, REFLEXOS, REPOUSO SEMANAL REMUNERADO E FERIADO, SUCUMBENCIAIS | K9: INSTRUÇÃO | L9: - | M9: AGUARDANDO AUDIÊNCIA | N9: 21/07/2026, ÀS 9:00. | O9: - | P9: EM ANDAMENTO | Q9: - | R9: - | S9: - | T9: - | U9: -
A10: 0001045-18.2025.5.14.0141 | B10: 46015 | C10: TRT 14° | D10: VILHENA | E10: WELLINGTON DA SILVA LIMA | F10: VF GOMES CONSTRUTORA | G10: ANA KAROLINE DA SILVA | H10: CRISDAINE MICAELI SILVA FAVALESSA SOUZA | I10: 547436 | J10: HONORÁRIOS ADVOCATÍCIOS, ADICIONAL NOTURNO, ADICIONAL DE HORAS EXTRAS, FGTS, FGTS, HORAS EXTRAS, HORAS EXTRAS, INTERVALO INTERJORNADAS, INTERVALO INTRAJORNADA, MULTA DE 40% DO FGTS, REFLEXOS, REPOUSO SEMANAL REMUNERADO E FERIADO, SUCUMBENCIAIS | K10: EXECUÇÃO | L10: 46059 | M10: AGUARDANDO PLANILHA ATUALIZADA DE CÁLCULOS PARA PAGAMENTO DOS IMPOSTOS | N10: - | O10: 324657.42 | P10: EM ANDAMENTO | Q10: SIM | R10: 210000 | S10: 214200 | T10: =I10-S10 -> 333236 | U10: -
A11: 0000195-50.2026.5.14.0101 | B11: 46118 | C11: TRT 14° | D11: OURO PRETO DO OESTE | E11: ADEVADLDO DENADAI | F11: VF GOMES CONSTRUTORA | G11: CLEITON DA SILVA ISABEL / ANA KAROLINE DA SILVA | H11: CRISDAINE MICAELI SILVA FAVALESSA SOUZA | I11: 141443.19 | J11: ADICIONAL DE HORAS EXTRAS, FGTS, HONORÁRIOS ADVOCATÍCIOS, HONORÁRIOS NA JUSTIÇA DO TRABALHO, HORAS EXTRAS, HORAS EXTRAS, INDENIZAÇÃO POR DANO MORAL, INTERVALO INTRAJORNADA, MULTA DE 40% DO FGTS, REFLEXOS | K11: RECURSO | L11: 46185 | M11: AGUARDANDO CONTRARRAZÕES DE EMBARGOS DE DECLARAÇÃO | N11: - | O11: - | P11: EM ANDAMENTO | Q11: - | R11: - | S11: - | T11: - | U11: -
A12: 0010314-47.2026.5.03.0046 | B12: 46160 | C12: TRT 3° | D12: ALMENARA | E12: GILVAN DE JESUS CUNHA | F12: VF GOMES CONSTRUTORA | G12: ANA KAROLINE DA SILVA | H12: KARYNY FELIPE DA SILVA / HEMILLY GOMES GUSMAO | I12: 69756.4 | J12: ADICIONAL DE INSALUBRIDADE | K12: INSTRUÇÃO | L12: - | M12: AGUARDANDO AUDIÊNCIA | N12: 31/07/2026, ÀS 17:30. | O12: - | P12: EM ANDAMENTO | Q12: - | R12: - | S12: - | T12: - | U12: -
A13: 0000305-83.2026.5.06.0291 | B13: 46123 | C13: TRT 6ª | D13: PALMARES | E13: JOSE ANDERSON DA SILVA | F13: VF GOMES CONSTRUTORA | G13: ANA KAROLINE DA SILVA | H13: LAYANNE RAFAELLY MARINHO HONORATO | I13: 27396.89 | J13: RESCISÃO INDIRETA | K13: EXECUÇÃO | L13: - | M13: CONCILIAÇÃO REALIZADA | N13: - | O13: - | P13: EM ANDAMENTO | Q13: SIM | R13: 5000 | S13: 6340 | T13: =I13-S13 -> 21056.89 | U13: -
A14: 0000083-40.2026.5.08.0104 | B14: 46097 | C14: TRT 8ª | D14: BREVES | E14: LOURIVAL DA SILVA MARINHO FILHO | F14: VF GOMES CONSTRUTORA | G14: ANA KAROLINE DA SILVA | H14: GENAISSON CAVALCANTE FEITOSA | I14: 127781.19 | J14: INDENIZAÇÃO POR DANO MORAL | K14: DECISÃO | L14: 46255 | M14: AGUARDANDO SENTENÇA | N14: - | O14: - | P14: EM ANDAMENTO | Q14: - | R14: - | S14: - | T14: - | U14: -
A15: 0000667-35.2025.5.08.0107 | B15: 45890 | C15: TRT 8ª | D15: 1° VARA / MARABÁ | E15: HIUELITON NUNES DE ARAÚJO | F15: VF GOMES CONSTRUTORA | G15: CLEITON DA SILVA ISABEL | H15: ROMOALDO JOSE OLIVEIRA DA SILVA / KAYLONPATRYCK DE OLIVEIRA CARNEIRO / DANILO ALBUQUERQUE DE CARVALHO | I15: 119237.63 | J15: HORAS EXTRAS, INDENIZAÇÃO POR DANO MORAL, INTERVALO INTRAJORNADA, SALÁRIO/DIFERENÇA SALARIAL | K15: RECURSO | L15: 46058 | M15: AGUARDANDO RECURSO | N15: - | O15: - | P15: RECURSO | Q15: - | R15: - | S15: - | T15: - | U15: -
A16: 0000114-21.2026.5.08.0117 | B16: 46064 | C16: TRT 8ª | D16: 2° / MARABÁ | E16: JOSIMAR DAS DORES FELIX | F16: VF GOMES CONSTRUTORA | G16: CLEITON DA SILVA ISABEL / ANA KAROLINE DA SILVA | H16: ROMOALDO JOSE OLIVEIRA DA SILVA / KAYLONPATRYCK DE OLIVEIRA CARNEIRO / DANILO ALBUQUERQUE DE CARVALHO | I16: 986655.72 | J16: INDENIZAÇÃO POR DANO MORAL, INDENIZAÇÃO POR DANO MATERIAL | K16: INSTRUÇÃO | L16: - | M16: AGUARDANDO AUDIÊNCIA | N16: 20/07/2026, ÀS 08:05. | O16: - | P16: EM ANDAMENTO | Q16: - | R16: - | S16: - | T16: - | U16: -
A17: 0000050-23.2026.5.08.0113 | B17: 46044 | C17: TRT 8ª | D17: ITAITUBA | E17: DHONES SILVA DE LIMA | F17: VF GOMES CONSTRUTORA | G17: CLEITON DA SILVA ISABEL / ANA KAROLINE DA SILVA | H17: WILLKERSON ROMEU LOPES / WERCELLI MARIA ANDRADE DOS SANTOS / NILSON NORMADES STRENZKE FILHO | I17: 216244.2 | J17: ADICIONAL DE INSALUBRIDADE | K17: INSTRUÇÃO | L17: - | M17: AGUARDANDO AUDIÊNCIA | N17: 04/08/2026, ÀS 09:00. | O17: - | P17: EM ANDAMENTO | Q17: - | R17: - | S17: - | T17: - | U17: -
A18: 0000371-49.2026.5.08.0116 | B18: 46106 | C18: TRT 8ª | D18: PARAGOMINAS | E18: ANTONIO FRANCISCO TINOCO GAMA | F18: VF GOMES CONSTRUTORA | G18: CLEITON DA SILVA ISABEL / ANA KAROLINE DA SILVA | H18: WILLKERSON ROMEU LOPES | I18: 56358.44 | J18: HORAS EXTRAS | K18: INICIAL | L18: - | M18: AGUARDANDO AUDIÊNCIA | N18: 02/07/2026, ÀS 08:45. | O18: - | P18: EM ANDAMENTO | Q18: - | R18: - | S18: - | T18: - | U18: -
A19: 0000343-90.2026.5.08.0113 | B19: 46128 | C19: TRT 8ª | D19: ITAITUBA | E19: GEANDERSON CORREA SOUZA | F19: VF GOMES CONSTRUTORA | G19: CLEITON DA SILVA ISABEL / ANA KAROLINE DA SILVA | H19: RUBENS AMARAL BERGAMINI / MIRELLE LETICIA GOULART DA SILVA | I19: 292768.43 | J19: RESCISÃO DO CONTRATO DE TRABALHO | K19: INICIAL | L19: - | M19: AGUARDANDO AUDIÊNCIA | N19: 01/09/2026, ÀS 10:00. | O19: - | P19: EM ANDAMENTO | Q19: - | R19: - | S19: - | T19: - | U19: -
A20: 0000364-54.2026.5.08.0117 | B20: 46136 | C20: TRT 8ª | D20: 2° / MARABÁ | E20: SEVERIANO SILVA SANTANA | F20: VF GOMES CONSTRUTORA | G20: ANA KAROLINE DA SILVA | H20: ROMOALDO JOSE OLIVEIRA DA SILVA / KAYLONPATRYCK DE OLIVEIRA CARNEIRO / DANILO ALBUQUERQUE DE CARVALHO | I20: 126498.75 | J20: HORAS EXTRAS, INDENIZAÇÃO POR DANO MORAL, INTERVALO INTRAJORNADA, MULTA DO ARTIGO 477 DA CLT, NULIDADE, VERBAS RESCISÓRIAS | K20: INSTRUÇÃO | L20: - | M20: AGUARDANDO AUDIÊNCIA | N20: 02/07/2026, ÀS 08:10. | O20: - | P20: EM ANDAMENTO | Q20: - | R20: - | S20: - | T20: - | U20: -
A21: 0000405-57.2026.5.08.0105 | B21: 46154 | C21: TRT 8ª | D21: CAPANEMA | E21: JOSE DE BRITO MOREIRA | F21: VF GOMES CONSTRUTORA | G21: - | H21: ESMERALDA PEDROSA GOMES | I21: 148652.97 | J21: AVISO PRÉVIO, ADICIONAL NOTURNO, ADICIONAL DE HORAS EXTRAS, FÉRIAS, FÉRIAS PROPORCIONAIS, HORAS EXTRAS, INDENIZAÇÃO POR DANO MORAL, REPOUSO SEMANAL REMUNERADO E FERIADO, RESCISÃO INDIRETA, SEGURO DESEMPREGO | K21: INICIAL | L21: - | M21: AGUARDANDO AUDIÊNCIA | N21: 28/09/2026, ÀS 10:00. | O21: - | P21: EM ANDAMENTO | Q21: - | R21: - | S21: - | T21: - | U21: -
A22: 0000469-43.2026.5.08.0113 | B22: 46162 | C22: TRT 8ª | D22: ITAITUBA | E22: MARCIO IVAN THEISEN | F22: VF GOMES LOCAÇÕES | G22: - | H22: EDU MARIANO DE SOUZA JUNIOR | I22: 147875.76 | J22: HORAS EXTRAS, ADICIONAL NOTURNO, HONORÁRIOS ADVOCATÍCIOS, INDENIZAÇÃO POR DANO MORAL, INTERVALO INTERJORNADAS, INTERVALO INTRAJORNADA, MULTA DO ARTIGO 467 DA CLT, REFLEXOS, SALÁRIO POR FORA - INTEGRAÇÃO, VERBAS RESCISÓRIAS | K22: INICIAL | L22: - | M22: AGUARDANDO AUDIÊNCIA | N22: 28/07/2026, ÀS 11:00. | O22: - | P22: EM ANDAMENTO | Q22: - | R22: - | S22: - | T22: - | U22: -
A23: 0000267-82.2026.5.10.0801 | B23: 46052 | C23: TRT 10ª | D23: PALMAS | E23: FRANKLLYN MIGUEL BARRETO MARTINS | F23: VF GOMES CONSTRUTORA | G23: ANA KAROLINE DA SILVA | H23: NEWTON CESAR DA SILVA LOPES / ANA CLÁUDIA PEREIRA DE MORAES | I23: 211489.59 | J23: ACÚMULO DE FUNÇÃO, ADICIONAL DE HORAS EXTRAS, ADICIONAL DE INSALUBRIDADE, DÉCIMO TERCEIRO SALÁRIO PROPORCIONAL, FÉRIAS PROPORCIONAIS, INDENIZAÇÃO POR DANO MORAL, MULTA DE 40% DO FGTS, REFLEXOS, VERBAS RESCISÓRIAS | K23: INSTRUÇÃO | L23: - | M23: AGUARDANDO AUDIÊNCIA | N23: 06/10/2026, ÀS 08:40. | O23: - | P23: EM ANDAMENTO | Q23: - | R23: - | S23: - | T23: - | U23: -
A24: 0001161-58.2026.5.10.0801 | B24: 46136 | C24: TRT 10ª | D24: PALMAS | E24: BRENO HALLIDEY DE SOUSA BRITO MARTINS | F24: VF GOMES CONSTRUTORA | G24: - | H24: NEWTON CESAR DA SILVA LOPES / ANA CLÁUDIA PEREIRA DE MORAES | I24: 288249.61 | J24: ADICIONAL DE INSALUBRIDADE, ADICIONAL DE PERICULOSIDADE, HORAS EXTRAS, INDENIZAÇÃO POR DANO MORAL, MULTA CONVENCIONAL, REFLEXOS, RESPONSABILIDADE SOLIDÁRIA/SUBSIDIÁRIA, SALÁRIO POR ACÚMULO DE CARGO/FUNÇÃO | K24: INICIAL | L24: - | M24: AGUARDANDO AUDIÊNCIA | N24: 27/07/2026, ÀS 11:45. | O24: - | P24: EM ANDAMENTO | Q24: - | R24: - | S24: - | T24: - | U24: -
A25: 0000538-44.2025.5.19.0262 | B25: 45980 | C25: TRT 19ª | D25: 2ª VARA DO TRABALHO DE SÃO MIGUEL DOS CAMPOS | E25: JOSE ALISSON VIEIRA DA SILVA | F25: VF GOMES CONSTRUTORA | G25: CLEITON DA SILVA ISABEL / ANA KAROLINE DA SILVA | H25: ANDRE RICARDO FERREIRA DE OLIVEIRA | I25: 73450 | J25: HORAS EXTRAS, ADICIONAL DE INSALUBRIDADE, MULTA DO ARTIGO 477 DA CLT, MULTA DO ARTIGO 467 DA CLT | K25: INSTRUÇÃO | L25: - | M25: AGUARDANDO AUDIÊNCIA | N25: 20/08/2026, ÀS 10:30. | O25: - | P25: EM ANDAMENTO | Q25: - | R25: - | S25: - | T25: - | U25: -
A26: 0000174-47.2026.5.23.0126 | B26: 46077 | C26: TRT 23ª | D26: CONFRESA | E26: FERNANDO MONTEIRO OLIVEIRA | F26: VF GOMES CONSTRUTORA | G26: ANA KAROLINE DA SILVA | H26: RANDERSON CARLOS FERREIRA DE MORAES / MILENE DA SILVA LIMA SANTOS / DEBORAH COELHO BARBOSA | I26: 92196.79 | J26: HORAS EXTRAS, ADICIONAL DE INSALUBRIDADE, AVISO PRÉVIO, CONDIÇÕES DEGRADANTES, INTERVALO INTRAJORNADA, REFLEXOS | K26: INSTRUÇÃO | L26: - | M26: AGUARDANDO PERICIA | N26: - | O26: - | P26: EM ANDAMENTO | Q26: - | R26: - | S26: - | T26: - | U26: -
A27: 0001185-21.2025.5.23.0038 | B27: 45982 | C27: TRT 23ª | D27: 3ª VARA / SINOP | E27: ARIELA RANGEL SARDI PELIZARIO | F27: VF GOMES PARTICIPAÇÕES | G27: ANA KAROLINE DA SILVA | H27: DEMETRIO BAGNO FERREIRA / ROBERTO CARLOS MELGAREJO DE VARGAS | I27: 150138.76 | J27: HORAS EXTRAS, ACÚMULO DE FUNÇÃO, ADICIONAL DE HORA EXTRA, ADICIONAL DE HORAS EXTRAS, ANOTAÇÃO/BAIXA/RETIFICAÇÃO, ASSÉDIO MORAL, CTPS, CARTÃO DE PONTO, CONTROLE DE JORNADA, DANO MORAL / MATERIAL, DESPEDIDA/DISPENSA IMOTIVADA, DESVIO DE FUNÇÃO, DIFERENÇAS POR DESVIO DE FUNÇÃO, DISPENSA / RESCISÃO DO CONTRATO DE TRABALHO, DISPENSA DISCRIMINATÓRIA, DÉCIMO TERCEIRO SALÁRIO, DÉCIMO TERCEIRO SALÁRIO PROPORCIONAL, FGTS, FGTS, FGTS, FERIADO EM DOBRO, FUNÇÃO DE CONFIANÇA - INCORPORAÇÃO, FÉRIAS, FÉRIAS / GOZO / FRUIÇÃO, FÉRIAS PROPORCIONAIS, GRATIFICAÇÃO DE FUNÇÃO, GRATIFICAÇÃO DE FÉRIAS, HONORÁRIOS ADVOCATÍCIOS, HONORÁRIOS PERICIAIS, HONORÁRIOS NA JUSTIÇA DO TRABALHO, HORA EXTRA/INTERVALO, HORAS EXTRAS, INDENIZAÇÃO POR DANO MORAL, INDENIZAÇÃO POR DANO MORAL, LEVANTAMENTO DO FGTS, MULTA DE 40% DO FGTS, REFLEXOS, SALÁRIO POR ACÚMULO DE CARGO/FUNÇÃO | K27: INSTRUÇÃO | L27: - | M27: AGUARDANDO AUDIÊNCIA | N27: 02/09/2026, ÀS 10:00. | O27: - | P27: EM ANDAMENTO | Q27: - | R27: - | S27: - | T27: - | U27: -
... A30: 0000543-14.2026.5.23.0038 | B30: 46164 | C30: TRT 23ª | D30: 3ª VARA / SINOP | E30: KATHIERE CANEDO GOMES | F30: VF GOMES PARTICIPAÇÕES | G30: SABRINA PAULA MARQUES FERRARINI | H30: ANA KAROLINE DA SILVA | I30: 7552.23 | J30: TERMO DE RESCISÃO CONTRATUAL | K30: INSTRUÇÃO | L30: - | M30: AGUARDANDO PERICIA | N30: - | O30: - | P30: EM ANDAMENTO | Q30: - | R30: - | S30: - | T30: - | U30: -
A31: 0000175-25.2026.5.23.0096 | B31: 46100 | C31: TRT 23ª | D31: PONTES E LACERDA | E31: GLEISON PANSERA BALDIN | F31: VF GOMES CONSTRUTORA | G31: JOAO PEDRO BORGES LOPES / GUSTAVO VIEIRA DO NASCIMENTO DE LIMA | H31: ANA KAROLINE DA SILVA | I31: 62212.09 | J31: RESCISÃO INDIRETA, ADICIONAL DE INSALUBRIDADE, ADICIONAL DE PERICULOSIDADE, AVISO PRÉVIO, DÉCIMO TERCEIRO SALÁRIO PROPORCIONAL, FGTS, FÉRIAS PROPORCIONAIS, HONORÁRIOS ADVOCATÍCIOS, INDENIZAÇÃO POR DANO MORAL, LEVANTAMENTO DO FGTS, MULTA DE 40% DO FGTS, MULTA DO ARTIGO 477 DA CLT, MULTA DO ARTIGO 467 DA CLT, SEGURO DESEMPREGO, SUSPENSÃO DA COBRANÇA - DEVEDOR BENEFICIÁRIO DE ASSISTÊNCIA JUDICIÁRIA GRATUITA | K31: INSTRUÇÃO | L31: - | M31: ENCERRADO | N31: - | O31: - | P31: ENCERRADO | Q31: SIM | R31: 10000 | S31: 13480.32 | T31: =I31-S31 -> 48731.77 | U31: -
A32: 0000601-89.2026.5.23.0111 | B32: 46176 | C32: TRT 23ª | D32: CAMPO NOVO DO PARECIS | E32: RYAN HENRIQUE SILVA SALOME | F32: VF GOMES CONSTRUTORA | G32: - | H32: CRISDAINE MICAELI SILVA FAVALESSA SOUZA | I32: 111225.49 | J32: HORAS EXTRAS, ADICIONAL NOTURNO, ADICIONAL DE HORAS EXTRAS, DEDUÇÃO/ABATIMENTO DE HORAS EXTRAS, DÉCIMO TERCEIRO SALÁRIO, DÉCIMO TERCEIRO SALÁRIO PROPORCIONAL, FGTS, FGTS, FGTS, HONORÁRIOS ADVOCATÍCIOS, HONORÁRIOS NA JUSTIÇA DO TRABALHO, HORAS EXTRAS, INDENIZAÇÃO/DOBRA/TERÇO CONSTITUCIONAL, INTERVALO INTRAJORNADA, LEVANTAMENTO DO FGTS, MULTA DE 40% DO FGTS, REFLEXOS, REPOUSO SEMANAL REMUNERADO E FERIADO, SUPRESSÃO/REDUÇÃO DE HORAS EXTRAS/INDENIZAÇÃO, TRABALHO AOS DOMINGOS | K32: INICIAL | L32: - | M32: AGUARDANDO AUDIÊNCIA | N32: 18/08/2026, ÀS 08:50. | O32: - | P32: EM ANDAMENTO | Q32: - | R32: - | S32: - | T32: - | U32: -
A33: 0000656-03.2026.5.06.0341 | B33: 46167 | C33: TRT 6ª | D33: PESQUEIRA | E33: ISRAEL NEPOSIANO ALVES SOBRAL | F33: VF GOMES CONSTRUTORA | G33: - | H33: FLAVIA OLIVEIRA LEITE | I33: 1260016.1 | J33: ACIDENTE DE TRABALHO, ACIDENTE DE TRABALHO, ESTABILIDADE ACIDENTÁRIA, INDENIZAÇÃO POR DANO ESTÉTICO, PENSÃO VITALÍCIA, RESCISÃO INDIRETA | K33: INICIAL | L33: - | M33: AGUARDANDO AUDIÊNCIA | N33: 10/07/2026, ÀS 08:45. | O33: - | P33: EM ANDAMENTO | Q33: - | R33: - | S33: - | T33: - | U33: -
A34: 0000381-59.2026.5.14.0041 | B34: 46195 | C34: TRT 14° | D34: CACOAL | E34: FABIO SANTOS DA SILVA | F34: VF GOMES CONSTRUTORA | G34: - | H34: CRISDAINE MICAELI SILVA FAVALESSA SOUZA | I34: 580090.67 | J34: DOENÇA OCUPACIONAL, DANO MORAL / MATERIAL, DOENÇA OCUPACIONAL, ESTABILIDADE ACIDENTÁRIA, HONORÁRIOS ADVOCATÍCIOS, INDENIZAÇÃO POR DANO MORAL, PENSÃO VITALÍCIA | K34: INICIAL | L34: - | M34: AGUARDANDO AUDIÊNCIA | N34: 07/07/2026, ÀS 08:40. | O34: - | P34: EM ANDAMENTO | Q34: - | R34: - | S34: - | T34: - | U34: -

Sheet DASHBOARD
A1: DASHBOARD - CONTROLE DE PROCESSOS TRABALHISTAS
B3: TOTAL DE CONDENAÇÃO | C3: TOTAL DE VALOR DE CAUSA | D3: TOTAL DE VALOR DE ACORDO | E3: VALOR TOTAL A PAGAR | F3: ZERADO | H3: ECONOMIA | J3: TOTAL DE PROCESSOS
B4: =SUM(PROCESSOS!O3:O100) -> 816428.3 | C4: =SUM(PROCESSOS!I3:I100) -> 6776535.9 | D4: =SUM(PROCESSOS!R3:R100) -> 225000 | E4: =SUM(PROCESSOS!S3:S100) -> 643231.55 | F4: =COUNTIF(PROCESSOS!S3:S100,F3) -> 1 | H4: =C4-E4 -> 6133304.4 | J4: =COUNTA(PROCESSOS!C3:C100) -> 32
R5: STATUS | S5: STATUS DE PROCESSOS
J6: FASE | K6: PROCESSOS POR FASE | R6: EM ANDAMENTO | S6: =COUNTIF(PROCESSOS!P3:P100,R6) -> 30
J7: RECURSO | K7: =COUNTIF(PROCESSOS!K3:K100,J7) -> 5 | R7: ENCERRADO | S7: =COUNTIF(PROCESSOS!P3:P100,R7) -> 1
J8: INSTRUÇÃO | K8: =COUNTIF(PROCESSOS!K3:K100,J8) -> 14 | R8: RECURSO | S8: =COUNTIF(PROCESSOS!P3:P100,R8) -> 1
J9: EXECUÇÃO | K9: =COUNTIF(PROCESSOS!K3:K100,J9) -> 3 | R9: SUSPENSO | S9: =COUNTIF(PROCESSOS!P3:P100,R9) -> 0
J10: DECISÃO | K10: =COUNTIF(PROCESSOS!K3:K100,J10) -> 1 | R10: ARQUIVADO | S10: =COUNTIF(PROCESSOS!P3:P100,R10) -> 0
J11: INICIAL | K11: =COUNTIF(PROCESSOS!K3:K100,J11) -> 9
B24: REGIÕES | C24: PROCESSOS POR REGIÃO | K24: ADVOGADOS RECLAMANTES | O24: QTD DE PROCESSOS
B25: TRT 3° | C25: =COUNTIF(PROCESSOS!C3:C100,B25) -> 1 | K25: GLORIA CHRIS GORDON | O25: =COUNTIF(PROCESSOS!H3:H100,K25 & "*") -> 4
B26: TRT 6ª | C26: =COUNTIF(PROCESSOS!C3:C100,B26) -> 2 | K26: GUILHERME RIBEIRO VENTURIN / JACKSON FRANCISCO OLIVEIRA | O26: =COUNTIF(PROCESSOS!H3:H100,K26 & "*") -> 1
B27: TRT 8ª | C27: =COUNTIF(PROCESSOS!C3:C100,B27) -> 9 | K27: CRISDAINE MICAELI SILVA FAVALESSA SOUZA | O27: =COUNTIF(PROCESSOS!H3:H100,K27 & "*") -> 6
B28: TRT 10ª | C28: =COUNTIF(PROCESSOS!C3:C100,B28) -> 2 | K28: KARYNY FELIPE DA SILVA / HEMILLY GOMES GUSMAO | O28: =COUNTIF(PROCESSOS!H3:H100,K28 & "*") -> 1
B29: TRT 14° | C29: =COUNTIF(PROCESSOS!C3:C100,B29) -> 10 | K29: LAYANNE RAFAELLY MARINHO HONORATO | O29: =COUNTIF(PROCESSOS!H3:H100,K29 & "*") -> 1
B30: TRT 19ª | C30: =COUNTIF(PROCESSOS!C3:C100,B30) -> 1 | K30: GENAISSON CAVALCANTE FEITOSA | O30: =COUNTIF(PROCESSOS!H3:H100,K30 & "*") -> 1
B31: TRT 23ª | C31: =COUNTIF(PROCESSOS!C3:C100,B31) -> 7 | K31: ROMOALDO JOSE OLIVEIRA DA SILVA / KAYLONPATRYCK DE OLIVEIRA CARNEIRO / DANILO ALBUQUERQUE DE CARVALHO | O31: =COUNTIF(PROCESSOS!H3:H100,K31 & "*") -> 3
K32: ESMERALDA PEDROSA GOMES | O32: =COUNTIF(PROCESSOS!H3:H100,K32 & "*") -> 1
K33: EDU MARIANO DE SOUZA JUNIOR | O33: =COUNTIF(PROCESSOS!H3:H100,K33 & "*") -> 1
B34: SITUAÇÃO | C34: PROCESSOS COM A SITUAÇÃO | K34: WILLKERSON ROMEU LOPES | O34: =COUNTIF(PROCESSOS!H3:H100,K34 & "*") -> 2
B35: AGUARDANDO AUDIÊNCIA | C35: =COUNTIF(PROCESSOS!M3:M100,B35) -> 19 | K35: RUBENS AMARAL BERGAMINI / MIRELLE LETICIA GOULART DA SILVA | O35: =COUNTIF(PROCESSOS!H3:H100,K35 & "*") -> 1
B36: AGUARDANDO PERICIA | C36: =COUNTIF(PROCESSOS!M3:M100,B36) -> 6 | K36: NEWTON CESAR DA SILVA LOPES / ANA CLÁUDIA PEREIRA DE MORAES | O36: =COUNTIF(PROCESSOS!H3:H100,K36 & "*") -> 2
B37: AGUARDANDO PLANILHA ATUALIZADA | C37: =COUNTIF(PROCESSOS!M3:M100,B37 & "*") -> 1 | K37: ANDRE RICARDO FERREIRA DE OLIVEIRA | O37: =COUNTIF(PROCESSOS!H3:H100,K37 & "*") -> 1
B38: AGUARDANDO CONTRARRAZÕES | C38: =COUNTIF(PROCESSOS!M3:M100,B38 & "*") -> 1 | K38: RANDERSON CARLOS FERREIRA DE MORAES / MILENE DA SILVA LIMA SANTOS / DEBORAH COELHO BARBOSA | O38: =COUNTIF(PROCESSOS!H3:H100,K38 & "*") -> 1
B39: AGUARDANDO SENTENÇA | C39: =COUNTIF(PROCESSOS!M3:M100,B39) -> 1 | K39: DEMETRIO BAGNO FERREIRA / ROBERTO CARLOS MELGAREJO DE VARGAS | O39: =COUNTIF(PROCESSOS!H3:H100,K39 & "*") -> 1
B40: CONCILIAÇÃO REALIZADA | C40: =COUNTIF(PROCESSOS!M3:M100,B40) -> 1 | K40: MIRELLE LETICIA GOULART DA SILVA | O40: =COUNTIF(PROCESSOS!H3:H100,K40 & "*") -> 1
B41: AGUARDANDO RECURSO | C41: =COUNTIF(PROCESSOS!M3:M100,B41) -> 1 | K41: PAULA FERREIRA AQUINO | O41: =COUNTIF(PROCESSOS!H3:H100,K41 & "*") -> 1
B42: AGUARDANDO CUMPRIMENTO DO ACORDO | C42: =COUNTIF(PROCESSOS!M3:M100,B42) -> 1 | K42: ANA KAROLINE DA SILVA | O42: =COUNTIF(PROCESSOS!H3:H100,K42 & "*") -> 2
B43: ENCERRADO | C43: =COUNTIF(PROCESSOS!M3:M100,B43) -> 1 | K43: FLAVIA OLIVEIRA LEITE | O43: =COUNTIF(PROCESSOS!H4:H101,K43 & "*") -> 1
B45: ADVOGADOS RECLAMADOS | C45: PROCESSOS COM ADVOGADOS RECLAMADOS
B46: CLEITON DA SILVA ISABEL | C46: =COUNTIF(PROCESSOS!G3:G100,B46) -> 4
B47: ANA KAROLINE DA SILVA | C47: =COUNTIF(PROCESSOS!G3:G100,B47) -> 12
B48: CLEITON DA SILVA ISABEL / ANA KAROLINE DA SILVA | C48: =COUNTIF(PROCESSOS!G3:G100,B48) -> 7
B49: SABRINA PAULA MARQUES FERRARINI | C49: =COUNTIF(PROCESSOS!G3:G100,B49) -> 1
B50: JOAO PEDRO BORGES LOPES / GUSTAVO VIEIRA DO NASCIMENTO | C50: =COUNTIF(PROCESSOS!G3:G100,B50 & "*") -> 1
B51: - | C51: =COUNTIF(PROCESSOS!G3:G100,B51) -> 7
